{"v":"5.7.14","fr":30,"ip":0,"op":121,"w":1080,"h":1080,"nm":"OH! V7","ddd":0,"assets":[],"fonts":{"list":[{"origin":0,"fPath":"","fClass":"","fFamily":"DynaPuff","fWeight":"","fStyle":"Black","fName":"DynaPuff-Black","ascent":79.6094385143369}]},"layers":[{"ddd":0,"ind":3,"ty":1,"nm":"Orange Solid 1","parent":4,"sr":1,"ks":{"o":{"a":0,"k":100,"ix":11},"r":{"a":0,"k":0,"ix":10},"p":{"a":0,"k":[334.779,58.75,0],"ix":2,"l":2},"a":{"a":0,"k":[400,400,0],"ix":1,"l":2},"s":{"a":0,"k":[98.75,98.75,100],"ix":6,"l":2}},"ao":0,"hasMask":true,"masksProperties":[{"inv":false,"mode":"f","pt":{"a":0,"k":{"i":[[0,0],[-34.843,2.161],[-35.352,136.726],[85.451,-11.033]],"o":[[34.843,-2.161],[-1.059,-141.219],[-85.451,11.033],[34.124,130.364]],"v":[[390.19,613.773],[494.72,607.291],[528.177,186.227],[271.824,219.325]],"c":true},"ix":1},"o":{"a":0,"k":100,"ix":3},"x":{"a":0,"k":0,"ix":4},"nm":"Mask 1"}],"sw":800,"sh":800,"sc":"#f49200","ip":0,"op":121,"st":0,"bm":0},{"ddd":0,"ind":4,"ty":1,"nm":"Orange Solid 1","sr":1,"ks":{"o":{"a":0,"k":100,"ix":11},"r":{"a":0,"k":0,"ix":10},"p":{"a":0,"k":[1014,712,0],"ix":2,"l":2},"a":{"a":0,"k":[400,400,0],"ix":1,"l":2},"s":{"a":0,"k":[72,72,100],"ix":6,"l":2}},"ao":0,"hasMask":true,"masksProperties":[{"inv":false,"mode":"f","pt":{"a":0,"k":{"i":[[79.604,-0.422],[-0.359,-35.512],[-79.545,25.556]],"o":[[-79.604,0.422],[0.359,35.512],[100.876,-32.409]],"v":[[413.436,309.381],[287.992,397.829],[411.491,465.485]],"c":true},"ix":1},"o":{"a":0,"k":100,"ix":3},"x":{"a":0,"k":0,"ix":4},"nm":"Mask 1"}],"sw":800,"sh":800,"sc":"#f49200","ip":0,"op":121,"st":0,"bm":0},{"ddd":0,"ind":5,"ty":5,"nm":"_txt_0","sr":1,"ks":{"o":{"a":0,"k":100,"ix":11},"r":{"a":0,"k":0,"ix":10},"p":{"a":0,"k":[422.876,879.296,0],"ix":2,"l":2},"a":{"a":0,"k":[-37.587,-200.155,0],"ix":1,"l":2},"s":{"a":0,"k":[120,120,100],"ix":6,"l":2}},"ao":0,"t":{"d":{"k":[{"s":{"sz":[752.76025390625,615.165222167969],"ps":[-383.317016601562,-761.235229492188],"s":500,"f":"DynaPuff-Black","t":"OH","ca":1,"j":2,"tr":0,"lh":253,"ls":0,"fc":[0.863,0.439,0.247],"sc":[1,1,1],"sw":0.00999999977648,"of":true,"vj":1,"rs":1,"m":1,"mc":10,"mf":50,"xf":500},"t":0}]},"p":{},"m":{"g":1,"a":{"a":0,"k":[0,0],"ix":2}},"a":[{"nm":"Animator 1","s":{"t":0,"xe":{"a":0,"k":0,"ix":7},"ne":{"a":0,"k":0,"ix":8},"a":{"a":0,"k":100,"ix":4},"b":1,"rn":0,"sh":1,"r":1},"a":{"ls":{"a":0,"k":[0,110],"ix":94}}}]},"ip":0,"op":121,"st":0,"bm":0}],"markers":[],"metadata":{"customProps":{"required-lines":1,"concept-map":"anger;celebration;congratulations;explosion;eye_roll;relieved;wink","keyword-map":"oh;ok;good bye;hello","line0-char-min":2,"line0-char-max":10,"line0-font-min":50,"line0-font-max":500,"alt-text":"animated text"}}}